odoo/addons/mrp_bom_attribute_match_semifinished_product/README.rst
odoo/addons/mrp_bom_attribute_match_semifinished_product/__init__.py
odoo/addons/mrp_bom_attribute_match_semifinished_product/__manifest__.py
odoo/addons/mrp_bom_attribute_match_semifinished_product/i18n/es.po
odoo/addons/mrp_bom_attribute_match_semifinished_product/i18n/it.po
odoo/addons/mrp_bom_attribute_match_semifinished_product/i18n/mrp_bom_attribute_match_semifinished_product.pot
odoo/addons/mrp_bom_attribute_match_semifinished_product/models/__init__.py
odoo/addons/mrp_bom_attribute_match_semifinished_product/models/product_template.py
odoo/addons/mrp_bom_attribute_match_semifinished_product/models/semi_finished_product_template_line.py
odoo/addons/mrp_bom_attribute_match_semifinished_product/readme/CONFIGURE.rst
odoo/addons/mrp_bom_attribute_match_semifinished_product/readme/CONTEXT.rst
odoo/addons/mrp_bom_attribute_match_semifinished_product/readme/DESCRIPTION.rst
odoo/addons/mrp_bom_attribute_match_semifinished_product/readme/USAGE.rst
odoo/addons/mrp_bom_attribute_match_semifinished_product/readme/newsfragments/.gitkeep
odoo/addons/mrp_bom_attribute_match_semifinished_product/security/ir.model.access.csv
odoo/addons/mrp_bom_attribute_match_semifinished_product/security/semifinished_product_security.xml
odoo/addons/mrp_bom_attribute_match_semifinished_product/static/description/icon.png
odoo/addons/mrp_bom_attribute_match_semifinished_product/static/description/index.html
odoo/addons/mrp_bom_attribute_match_semifinished_product/tests/__init__.py
odoo/addons/mrp_bom_attribute_match_semifinished_product/tests/test_finished_product_common.py
odoo/addons/mrp_bom_attribute_match_semifinished_product/tests/test_finished_product_structure.py
odoo/addons/mrp_bom_attribute_match_semifinished_product/tests/test_product_template.py
odoo/addons/mrp_bom_attribute_match_semifinished_product/views/product_template_views.xml
odoo14_addon_mrp_bom_attribute_match_semifinished_product-14.0.1.0.4.dist-info/METADATA
odoo14_addon_mrp_bom_attribute_match_semifinished_product-14.0.1.0.4.dist-info/WHEEL
odoo14_addon_mrp_bom_attribute_match_semifinished_product-14.0.1.0.4.dist-info/top_level.txt
odoo14_addon_mrp_bom_attribute_match_semifinished_product-14.0.1.0.4.dist-info/RECORD
